ebau_gwr/__init__.py
ebau_gwr/linker/__init__.py
ebau_gwr/linker/apps.py
ebau_gwr/linker/conftest.py
ebau_gwr/linker/factories.py
ebau_gwr/linker/filters.py
ebau_gwr/linker/migrations/0001_initial.py
ebau_gwr/linker/migrations/0002_set_default_ordering.py
ebau_gwr/linker/migrations/0003_deprecated_json_field.py
ebau_gwr/linker/migrations/__init__.py
ebau_gwr/linker/models.py
ebau_gwr/linker/serializers.py
ebau_gwr/linker/urls.py
ebau_gwr/linker/views.py
ebau_gwr/oidc_auth/__init__.py
ebau_gwr/oidc_auth/authentication.py
ebau_gwr/oidc_auth/models.py
ebau_gwr/settings.py
ebau_gwr/token_proxy/__init__.py
ebau_gwr/token_proxy/app_settings.py
ebau_gwr/token_proxy/apps.py
ebau_gwr/token_proxy/client.py
ebau_gwr/token_proxy/factories.py
ebau_gwr/token_proxy/management/__init__.py
ebau_gwr/token_proxy/management/commands/__init__.py
ebau_gwr/token_proxy/management/commands/generate_fernet_key.py
ebau_gwr/token_proxy/migrations/0001_initial.py
ebau_gwr/token_proxy/migrations/0002_housingstatcreds_municipality.py
ebau_gwr/token_proxy/migrations/0003_housingstatcreds_group.py
ebau_gwr/token_proxy/migrations/0004_alter_housingstatcreds_owner.py
ebau_gwr/token_proxy/migrations/__init__.py
ebau_gwr/token_proxy/models.py
ebau_gwr/token_proxy/serializers.py
ebau_gwr/token_proxy/urls.py
ebau_gwr/token_proxy/views.py
ebau_gwr/urls.py
ebau_gwr/wsgi.py
ebau_gwr-0.8.3.dist-info/METADATA
ebau_gwr-0.8.3.dist-info/WHEEL
ebau_gwr-0.8.3.dist-info/licenses/LICENSE
ebau_gwr-0.8.3.dist-info/RECORD
