Metadata-Version: 2.4
Name: ebau-gwr
Version: 0.8.3
Summary: GWR synchronisation for ebau projects
License: GPL-3.0-or-later
License-File: LICENSE
Author: Adfinis AG
Requires-Python: >=3.12,<4
Classifier: Development Status :: 5 - Production/Stable
Classifier: Environment :: Web Environment
Classifier: Framework :: Django :: 3.2
Classifier: Intended Audience :: Developers
Classifier: License :: OSI Approved :: GNU General Public License v3 (GPLv3)
Classifier: License :: OSI Approved :: GNU General Public License v3 or later (GPLv3+)
Classifier: Operating System :: OS Independent
Classifier: Programming Language :: Python :: 3
Classifier: Programming Language :: Python :: 3.12
Classifier: Programming Language :: Python :: 3.13
Classifier: Programming Language :: Python :: 3.14
Requires-Dist: Django (>=4.2,<5.3)
Requires-Dist: cryptography (>=37.0.2,<46)
Requires-Dist: django-environ (>=0.10,<0.13)
Requires-Dist: django-filter (>=23.5,<26)
Requires-Dist: django-generic-api-permissions (>=1.0.0,<4)
Requires-Dist: djangorestframework (>=3.14.0,<4.0.0)
Requires-Dist: djangorestframework-jsonapi (>=5,<9)
Requires-Dist: mozilla-django-oidc (>=2,<5)
Requires-Dist: psycopg-binary (>=3.2.1,<4.0.0)
Requires-Dist: psycopg[binary] (>=3.2.1,<4.0.0)
Requires-Dist: requests (>=2.31.0,<3.0.0)
Requires-Dist: uWSGI (>=2.0.23,<3.0.0)
Project-URL: Homepage, https://github.com/inosca/ebau-gwr
Project-URL: Repository, https://github.com/inosca/ebau-gwr
